parallel_reqs/__init__.py
parallel_reqs/main.py
parallel_reqs/request/__init__.py
parallel_reqs/request/request_executor.py
parallel_reqs/request/requests.py
parallel_reqs/response/__init__.py
parallel_reqs/response/response.py
tests/__init__.py
tests/test_executor.py
tests/test_requests.py
parallel_reqs-0.0.5.dist-info/METADATA
parallel_reqs-0.0.5.dist-info/WHEEL
parallel_reqs-0.0.5.dist-info/entry_points.txt
parallel_reqs-0.0.5.dist-info/top_level.txt
parallel_reqs-0.0.5.dist-info/RECORD
