Metadata-Version: 2.1
Name: parallel_reqs
Version: 0.0.5
Summary: Calling parallel request Pyhton
Home-page: https://github.com/danelsan/parallel-requests
Author: Daniele Frulla
Author-email: daniele.frulla@newstechnology.eu
Classifier: Programming Language :: Python :: 3
Classifier: License :: OSI Approved :: MIT License
Classifier: Operating System :: OS Independent
Requires-Python: >=3.6
Requires-Dist: aiohttp
